memary/__init__.py
memary/agent/__init__.py
memary/agent/base_agent.py
memary/agent/chat_agent.py
memary/agent/data_types.py
memary/agent/llm_api/tools.py
memary/memory/__init__.py
memary/memory/base_memory.py
memary/memory/entity_knowledge_store.py
memary/memory/memory_stream.py
memary/memory/types.py
memary/synonym_expand/__init__.py
memary/synonym_expand/output.py
memary/synonym_expand/synonym.py
memary-0.1.3.dist-info/METADATA
memary-0.1.3.dist-info/WHEEL
memary-0.1.3.dist-info/licenses/LICENSE
memary-0.1.3.dist-info/RECORD
