Metadata-Version: 2.3
Name: memary
Version: 0.1.3
Summary: Longterm Memory for Autonomous Agents
Project-URL: Homepage, https://github.com/kingjulio8238/memary
Project-URL: Issues, https://github.com/kingjulio8238/memary/issues
Author-email: memary Labs <hello@memarylabs.com>
License-File: LICENSE
Classifier: License :: OSI Approved :: MIT License
Classifier: Operating System :: OS Independent
Classifier: Programming Language :: Python :: 3
Requires-Python: <=3.11.9,>=3.8
Requires-Dist: ansistrip
Requires-Dist: geocoder
Requires-Dist: googlemaps
Requires-Dist: langchain-openai==0.0.8
Requires-Dist: langchain==0.1.12
Requires-Dist: llama-index-agent-openai==0.1.5
Requires-Dist: llama-index-core==0.10.12
Requires-Dist: llama-index-embeddings-openai==0.1.5
Requires-Dist: llama-index-graph-stores-nebula==0.1.2
Requires-Dist: llama-index-graph-stores-neo4j==0.1.1
Requires-Dist: llama-index-legacy==0.9.48
Requires-Dist: llama-index-llms-ollama==0.1.2
Requires-Dist: llama-index-llms-openai==0.1.5
Requires-Dist: llama-index-llms-perplexity==0.1.3
Requires-Dist: llama-index-multi-modal-llms-ollama==0.1.3
Requires-Dist: llama-index-multi-modal-llms-openai==0.1.3
Requires-Dist: llama-index-program-openai==0.1.3
Requires-Dist: llama-index-question-gen-openai==0.1.2
Requires-Dist: llama-index-readers-file==0.1.4
Requires-Dist: llama-index==0.10.11
Requires-Dist: neo4j==5.17.0
Requires-Dist: numpy
Requires-Dist: ollama
Requires-Dist: pandas
Requires-Dist: python-dotenv==1.0.1
Requires-Dist: pyvis==0.3.2
Requires-Dist: streamlit==1.31.1
